[
  {
    "npi": "1396741351",
    "name": "Dr. Tien Nguyen",
    "specialty": "Dermatology",
    "city": "Fountain Valley",
    "region": "SoCal",
    "cost": 1591479,
    "clms": 224,
    "mom": 20,
    "daysSinceVisit": 169,
    "tag": "lapsed"
  },
  {
    "npi": "1083892236",
    "name": "Dr. Chris Towery",
    "specialty": "Physician Assistant",
    "city": "Santa Clarita",
    "region": "SoCal",
    "cost": 1006538,
    "clms": 142,
    "mom": -21,
    "daysSinceVisit": 109,
    "tag": "declining"
  },
  {
    "npi": "1831614353",
    "name": "Dr. Khanh Ngoc Ton Nu",
    "specialty": "Physician Assistant",
    "city": "Westminster",
    "region": "SoCal",
    "cost": 672495,
    "clms": 94,
    "mom": 17,
    "daysSinceVisit": 97,
    "tag": null
  },
  {
    "npi": "1902867294",
    "name": "Dr. Pierre Labrecque",
    "specialty": "Dermatology",
    "city": "Santa Maria",
    "region": "SoCal",
    "cost": 623446,
    "clms": 92,
    "mom": -5,
    "daysSinceVisit": 113,
    "tag": "lapsed"
  },
  {
    "npi": "1831300722",
    "name": "Dr. Sheri Hsu",
    "specialty": "Rheumatology",
    "city": "La Quinta",
    "region": "SoCal",
    "cost": 496205,
    "clms": 67,
    "mom": 6,
    "daysSinceVisit": 105,
    "tag": "lapsed"
  },
  {
    "npi": "1326340308",
    "name": "Dr. Michael Elist",
    "specialty": "Rheumatology",
    "city": "Tarzana",
    "region": "SoCal",
    "cost": 467443,
    "clms": 62,
    "mom": 45,
    "daysSinceVisit": 140,
    "tag": "rising"
  },
  {
    "npi": "1245753839",
    "name": "Dr. Sheryl Miles",
    "specialty": "Physician Assistant",
    "city": "Santa Maria",
    "region": "SoCal",
    "cost": 446405,
    "clms": 63,
    "mom": -24,
    "daysSinceVisit": 5,
    "tag": "declining"
  },
  {
    "npi": "1720074537",
    "name": "Dr. Paul Yamauchi",
    "specialty": "Dermatology",
    "city": "Santa Monica",
    "region": "SoCal",
    "cost": 422744,
    "clms": 61,
    "mom": 48,
    "daysSinceVisit": 97,
    "tag": "rising"
  },
  {
    "npi": "1952460859",
    "name": "Dr. Noune Pashinian",
    "specialty": "Rheumatology",
    "city": "Glendale",
    "region": "SoCal",
    "cost": 410266,
    "clms": 42,
    "mom": 0,
    "daysSinceVisit": 54,
    "tag": null
  },
  {
    "npi": "1629002191",
    "name": "Dr. Christina Kim",
    "specialty": "Dermatology",
    "city": "Los Angeles",
    "region": "SoCal",
    "cost": 409986,
    "clms": 84,
    "mom": 16,
    "daysSinceVisit": 9,
    "tag": null
  },
  {
    "npi": "1104110071",
    "name": "Dr. Navid Ezra",
    "specialty": "Dermatology",
    "city": "Thousand Oaks",
    "region": "SoCal",
    "cost": 400107,
    "clms": 53,
    "mom": -23,
    "daysSinceVisit": 49,
    "tag": "declining"
  },
  {
    "npi": "1346380748",
    "name": "Dr. Heather Gillespie",
    "specialty": "Rheumatology",
    "city": "Moreno Valley",
    "region": "SoCal",
    "cost": 398516,
    "clms": 48,
    "mom": -22,
    "daysSinceVisit": 43,
    "tag": "declining"
  }
]